setup.py
scriptmodule/__init__.py
scriptmodule.egg-info/PKG-INFO
scriptmodule.egg-info/SOURCES.txt
scriptmodule.egg-info/dependency_links.txt
scriptmodule.egg-info/top_level.txt
scriptmodule/enums/__init__.py
scriptmodule/enums/menuaction.py
scriptmodule/enums/threadstatus.py
scriptmodule/widgets/__init__.py
scriptmodule/widgets/scrolllabel.py