Metadata-Version: 2.1
Name: scriptmodule
Version: 0.0.1
Summary: i donot know too
Home-page: https://pypi.org/
Author: cwc
Author-email: idonotknow@idonotknow.com
Classifier: Programming Language :: Python :: 3
Classifier: License :: OSI Approved :: Apache Software License
Classifier: Operating System :: OS Independent
